vm/main.py
vm/libvm.so
vm/__init__.py
uza-0.0.2.data/data/lib/libvm.so
uzac/bytecode.py
uzac/token.py
uzac/builtins.py
uzac/__main__.py
uzac/driver.py
uzac/type.py
uzac/ast.py
uzac/interpreter.py
uzac/utils.py
uzac/__init__.py
uzac/typer.py
uzac/cli.py
uzac/parser.py
uza-0.0.2.dist-info/LICENSE
uza-0.0.2.dist-info/WHEEL
uza-0.0.2.dist-info/RECORD
uza-0.0.2.dist-info/top_level.txt
uza-0.0.2.dist-info/entry_points.txt
uza-0.0.2.dist-info/METADATA
