Metadata-Version: 2.2
Name: uza
Version: 0.0.2
Summary: A compiler and bytecode interpreter for the uza programming language
Author: M. Sanchez Lopez
License: MIT License
Keywords: compiler,interpreter,programming language
Requires-Python: >=3.10
License-File: LICENSE
Provides-Extra: dev
Requires-Dist: pytest; extra == "dev"
Requires-Dist: mypy; extra == "dev"
Requires-Dist: pylint; extra == "dev"
Requires-Dist: ruff; extra == "dev"
Requires-Dist: pre-commit; extra == "dev"
Dynamic: requires-python
